Workbook
Name BuyerCode: [1]!Buyer1[Code]
Name CompanyCode: [1]!Company1[Company]
Name CompanyName: '[1]003-Info'!$S$1:$S$10
Name DeptCode: [1]!Dept1[Code]
Name DivisionCode: [1]!Company1[Division]
Name FacilityCode: [1]!Facility1[Code]

Sheet Month Wise Sales Qty
A1: TEAM LEAD | B1: WASH TYPE | C1: CUSTOMER | D1: 46204 | E1: 46235 | F1: 46266 | G1: 46296 | H1: 46327 | I1: 46357 | J1: 46388 | K1: 46419 | L1: 46447 | M1: 46478 | N1: 46508 | O1: 46539 | P1: Total
A2: NAQEEB | B2: NON DENIM | C2: JACK & JONES | D2: 92000 | E2: 81000 | F2: 161000 | G2: 120000 | H2: =100000+30000 -> 130000 | I2: =130000-30000 -> 100000 | J2: 100000 | K2: 100000 | L2: 100000 | M2: 100276.35 | N2: =110000-60000+5000 -> 55000 | O2: =100000-30000 -> 70000 | P2: =SUM(D2:O2) -> 1209276.3
A3: NAQEEB | B3: DENIM | C3: NAME IT | D3: 42000 | E3: 38000 | F3: 50000 | G3: 50000 | H3: 50000 | I3: 30000 | J3: 40000 | K3: 30000 | L3: 50000 | M3: 35000 | N3: 35000 | O3: 35000 | P3: =SUM(D3:O3) -> 485000
A4: NAQEEB | B4: NON DENIM | C4: Vero Moda | I4: 10000 | J4: 10000 | M4: 5000 | N4: 5000 | O4: 5000 | P4: =SUM(D4:O4) -> 35000
A5: NAQEEB | B5: DENIM | C5: BLACK DIAMOND | E5: 51000 | I5: 30000 | M5: 20000 | N5: 15000 | O5: 10000 | P5: =SUM(D5:O5) -> 126000
A6: NAQEEB | B6: NON DENIM | C6: GLORIA JEANS | H6: 10000 | K6: 5000 | M6: 7500 | N6: 10000 | O6: 10000 | P6: =SUM(D6:O6) -> 42500
A7: NAQEEB | B7: NON DENIM | C7: NEMESIS | D7: 29000 | K7: 10000 | O7: 20000 | P7: =SUM(D7:O7) -> 59000
A8: RIZWAN | B8: DENIM | C8: HERO/STOOKER | D8: 99000 | E8: 50000 | F8: 35000 | G8: 50000 | H8: 90000 | I8: 50000 | J8: 35000 | K8: 30000 | L8: 35000 | M8: 45000 | N8: 45000 | O8: 65000 | P8: =SUM(D8:O8) -> 629000
A9: RIZWAN | B9: NON DENIM | C9: SORBINO | D9: 0 | E9: 0 | F9: 35000 | G9: 25000 | H9: 15000 | I9: 50000 | J9: 60000 | K9: 60000 | L9: 20000 | M9: 10000 | N9: 0 | O9: 10000 | P9: =SUM(D9:O9) -> 285000
A10: RIZWAN | B10: NON DENIM | C10: ELVIN | G10: 0 | H10: 0 | I10: 25000 | J10: 0 | L10: 40000 | M10: 15000 | N10: 10000 | O10: 25000 | P10: =SUM(D10:O10) -> 115000
A11: RIZWAN | B11: DENIM | C11: ORIGINAL MARINE | G11: 20000 | H11: 10000 | K11: 15000 | L11: 15000 | O11: 15000 | P11: =SUM(D11:O11) -> 75000
A12: RIZWAN | B12: NON DENIM | C12: SWING JEANS | G12: 20000 | H12: 0 | L12: 15000 | M12: 15000 | N12: 15000 | O12: 15000 | P12: =SUM(D12:O12) -> 80000
A13: RIZWAN | B13: DENIM | C13: NEW YORKER | E13: 45000 | F13: 86000 | G13: 25000 | H13: 75000 | I13: 50000 | J13: 20000 | K13: 20000 | L13: 20000 | M13: 40000 | N13: 75000 | O13: 50000 | P13: =SUM(D13:O13) -> 506000
A14: RIZWAN | B14: DENIM | C14: LPP | D14: 5000 | E14: 0 | F14: 0 | G14: 0 | H14: 0 | I14: 0 | J14: 5000 | K14: 15000 | L14: 20000 | M14: 15000 | N14: 20000 | O14: 15000 | P14: =SUM(D14:O14) -> 95000
A15: RIZWAN | B15: NON DENIM | C15: ECONOVA | E15: 0 | F15: 18000 | G15: 18000 | H15: 6000 | I15: 6000 | J15: 9000 | K15: 9000 | L15: 21000 | M15: 12000 | N15: 21000 | O15: 15000 | P15: =SUM(D15:O15) -> 135000
A16: RIZWAN | B16: DENIM | C16: ECONOVA | F16: 12000 | G16: 12000 | H16: 4000 | I16: 4000 | J16: 6000 | K16: 6000 | L16: 14000 | M16: 8000 | N16: 14000 | O16: 10000 | P16: =SUM(D16:O16) -> 90000
A17: DEEP | B17: DENIM | C17: AEROPOSTALE | D17: 11900 | E17: 53668 | F17: 24016 | G17: 35000 | H17: 40000 | I17: 40000 | J17: 15000 | K17: 35000 | L17: 15000 | M17: 35000 | N17: 40000 | O17: 40000 | P17: =SUM(D17:O17) -> 384584
A18: DEEP | B18: NON DENIM | C18: AEROPOSTALE | I18: 10000 | J18: 0 | K18: 5000 | L18: 10000 | M18: 15000 | N18: 15000 | O18: 15000 | P18: =SUM(D18:O18) -> 70000
A19: DEEP | B19: DENIM | C19: LUCKY BRANDS | D19: 11900 | E19: 53668 | F19: 24016 | G19: 35000 | H19: 40000 | I19: 40000 | J19: 25000 | K19: 25000 | L19: 35000 | M19: 35000 | N19: 40000 | O19: 40000 | P19: =SUM(D19:O19) -> 404584
A20: DEEP | B20: NON DENIM | C20: FASHION NOVA | D20: 14220 | E20: 10720 | F20: 15000 | G20: 15000 | H20: 15000 | I20: 15000 | J20: 15000 | K20: 15000 | L20: 15000 | M20: 10000 | N20: 15000 | O20: 15000 | P20: =SUM(D20:O20) -> 169940
A21: DEEP | B21: DENIM | C21: RMIXED | G21: 0 | I21: 5000 | K21: 0 | L21: 0 | M21: 0 | O21: 5000 | P21: =SUM(D21:O21) -> 10000
A22: DEEP | B22: NON DENIM | C22: SCANDIC | I22: 5000 | J22: 5000 | K22: 5000 | L22: 10000 | M22: 10000 | N22: 10000 | O22: 10000 | P22: =SUM(D22:O22) -> 55000
A23: DEEP | B23: DENIM | C23: SCANDIC | I23: 5000 | J23: 5000 | K23: 5000 | L23: 10000 | M23: 10000 | N23: 10000 | O23: 10000 | P23: =SUM(D23:O23) -> 55000
A24: DEEP | B24: DENIM | C24: INDITEX | I24: 20000 | J24: 10000 | K24: 10000 | L24: 15000 | M24: 10000 | N24: 20000 | O24: 20000 | P24: =SUM(D24:O24) -> 105000
A25: DEEP | B25: DENIM | C25: UK MKT | I25: 20000 | J25: 20000 | L25: 15000 | M25: 10000 | N25: 20000 | O25: 20000 | P25: =SUM(D25:O25) -> 105000
A26: RASHID | B26: DENIM | C26: KIABI MEN | M26: 20000 | N26: 20000 | O26: 20000 | P26: =SUM(D26:O26) -> 60000
A27: RASHID | B27: NON DENIM | C27: KIABI MEN | D27: 45000 | E27: 19000 | F27: 20000 | G27: 39000 | H27: 39000 | I27: 39000 | J27: 33000 | K27: 27000 | L27: 21000 | M27: 27000 | N27: 39000 | O27: 39000 | P27: =SUM(D27:O27) -> 387000
A28: RASHID | B28: NON DENIM | C28: KIABI KIDS | D28: 50000 | E28: 16000 | F28: 50000 | G28: 91000 | H28: 91000 | I28: 91000 | J28: 77000 | K28: 63000 | L28: 49000 | M28: 63000 | N28: 91000 | O28: 91000 | P28: =SUM(D28:O28) -> 823000
A29: FARRUKH | B29: DENIM | C29: C&A MEN | D29: 22500 | E29: 0 | F29: 30000 | G29: 30000 | H29: 12000 | I29: 8000 | J29: 20000 | K29: 20000 | L29: 25000 | M29: 22000 | N29: 12000 | O29: 8000 | P29: =SUM(D29:O29) -> 209500
A30: FARRUKH | B30: NON DENIM | C30: C&A MEN | D30: 242000 | E30: =250000-10000 -> 240000 | F30: =50000-10000 -> 40000 | G30: =50000+10000 -> 60000 | H30: 30000 | I30: =20000-10000 -> 10000 | J30: 180000 | K30: 75000 | L30: =100000-100000 -> 0 | M30: =88000-75000+10000+10000 -> 33000 | N30: 0 | O30: 0 | P30: =SUM(D30:O30) -> 910000
A31: FARRUKH | B31: DENIM | C31: C&A LADIES | D31: 0 | E31: 0 | F31: 56000 | G31: 91000 | H31: 42000 | I31: 42000 | J31: 35000 | K31: 35000 | L31: =70000-40000 -> 30000 | M31: =67000+3000 -> 70000 | N31: 0 | O31: 0 | P31: =SUM(D31:O31) -> 401000
A32: FARRUKH | B32: NON DENIM | C32: C&A LADIES | F32: 24000 | G32: 39000 | H32: 18000 | I32: 18000 | J32: 15000 | K32: 15000 | L32: 30000 | M32: 28000 | N32: 18000 | O32: 18000 | P32: =SUM(D32:O32) -> 223000
A33: FARRUKH | B33: DENIM | C33: C&A-KIDS | D33: 9000 | E33: 9000 | F33: 0 | G33: 0 | H33: 20000 | I33: 20000 | J33: 20000 | K33: 20000 | L33: 20000 | M33: 20000 | N33: 20000 | O33: 20000 | P33: =SUM(D33:O33) -> 178000
A34: FARRUKH | B34: NON DENIM | C34: C&A-KIDS | H34: 10000 | I34: 10000 | J34: 10000 | K34: 10000 | L34: 10000 | M34: 10000 | N34: 10000 | O34: 10000 | P34: =SUM(D34:O34) -> 80000
D35: =SUM(D2:D34) -> 673520 | E35: =SUM(E2:E34) -> 667056 | F35: =SUM(F2:F34) -> 680032 | G35: =SUM(G2:G34) -> 775000 | H35: =SUM(H2:H34) -> 747000 | I35: =SUM(I2:I34) -> 753000 | J35: =SUM(J2:J34) -> 770000 | K35: =SUM(K2:K34) -> 665000 | ... P35: =SUM(P2:P34) -> 8597384.3

Sheet Costing Grid
A1: Team | B1: Wash Type | C1: Payment Term | D1: Customer | E1: Qty | F1: Fabric Cons | G1: Fab Price | H1: Fabric | I1: Pocket Cons | J1: Pocketing Price | K1: Pocketing | L1: Trim | M1: Testing | N1: Sampling | O1: Chemical | P1: SAM | Q1: Total SAM | R1: Wash OH | S1: OH | T1: Freight | U1: Waste % | V1: Wastage | W1: Finance Cost | X1: Commission | Y1: Comm %age | Z1: Profit | AA1: Vol % | AB1: Cost Price | AC1: Check | AD1: Provided FOB | AE1: Addition | AF1: Target FOB | AG1: CM | AH1: Per Min CM | AI1: Per Min CM USD | AJ1: Value (CM) USD | AK1: Value (CM) PKR | AL1: CM/ Minute | AM1: FOB Value | AN1: Parity Rate | AO1: Total Profit | AP1: Total Fabric Cost | AQ1: Total Pocketing | AR1: Total Trim | AS1: Total Testing | AT1: Total Sampling | AU1: Total Chemical | AV1: Total Wash OH | AW1: Total Freight Cost | AX1: Total Finance Cost | AY1: Total Commission | AZ1: Total Variable Cost | BA1: Total Contribution | BB1: Overheads | BC1: Net Profit | BD1: Code | BE1: Check2
A2: ='Month Wise Sales Qty'!A2 -> NAQEEB | B2: ='Month Wise Sales Qty'!B2 -> NON DENIM | D2: ='Month Wise Sales Qty'!C2 -> JACK & JONES | E2: =SUMIFS('Month Wise Sales Qty'!P:P,'Month Wise Sales Qty'!C:C,Table4[[#This Row],[Customer]],'Month Wise Sales Qty'!B:B,Table4[[#This Row],[Wash Type]],'Month Wise Sales Qty'!A:A,Table4[[#This Row],[Team]]) -> 1209276.3 | H2: =Table4[[#This Row],[Fabric Cons]]*Table4[[#This Row],[Fab Price]] -> 0 | K2: =Table4[[#This Row],[Pocket Cons]]*Table4[[#This Row],[Pocketing Price]] -> 0 | Q2: =P2*E2 -> 0 | V2: =(H2+K2+L2+O2)*U2% -> 0 | Y2: =IFERROR(X2/AB2,0) -> 0 | Z2: =Table4[[#This Row],[Target FOB]]-Table4[[#This Row],[Cost Price]] -> 0 | AA2: =IFERROR(Table4[[#This Row],[Total SAM]]/$Q$36,0) -> 0 | AB2: =SUM(V2:X2,R2:T2,K2:O2,H2) -> 0 | AC2: =AF2-AB2 -> 0 | AE2: 0 | AF2: =Table4[[#This Row],[Provided FOB]]+Table4[[#This Row],[Addition]] -> 0 | AG2: =Z2+S2 -> 0 | AH2: =IFERROR(AJ2*AN2/Q2,0) -> 0 | AI2: =IFERROR(Table4[[#This Row],[Per Min CM ]]/Table4[[#This Row],[Parity Rate]],0)*100 -> 0 | AJ2: =AG2*E2 -> 0 | AK2: =AJ2*AN2 -> 0 | AL2: =IFERROR(AK2/Q2,0) -> 0 | AM2: =AF2*E2 -> 0 | AO2: =Z2*E2 -> 0 | AP2: =$E2*H2*(1+$U2%) -> 0 | AQ2: =$E2*K2*(1+$U2%) -> 0 | AR2: =$E2*L2*(1+$U2%) -> 0 | AS2: =$E2*M2 -> 0 | AT2: =$E2*N2 -> 0 | AU2: =$E2*O2*(1+$U2%) -> 0 | AV2: =$E2*R2 -> 0 | AW2: =$E2*T2 -> 0 | AX2: =$E2*W2 -> 0 | AY2: =$E2*X2 -> 0 | AZ2: =SUM(AP2:AY2) -> 0 | BA2: =AM2-AZ2 -> 0 | BB2: =Table4[[#This Row],[OH ]]*Table4[[#This Row],[Qty]] -> 0 | BC2: =Table4[[#This Row],[Total Contribution]]-Table4[[#This Row],[Overheads]] -> 0 | BD2: =B2&D2 -> NON DENIMJACK & JONES | BE2: =AJ2-BA2 -> 0
A3: ='Month Wise Sales Qty'!A3 -> NAQEEB | B3: ='Month Wise Sales Qty'!B3 -> DENIM | D3: ='Month Wise Sales Qty'!C3 -> NAME IT | E3: =SUMIFS('Month Wise Sales Qty'!P:P,'Month Wise Sales Qty'!C:C,Table4[[#This Row],[Customer]],'Month Wise Sales Qty'!B:B,Table4[[#This Row],[Wash Type]],'Month Wise Sales Qty'!A:A,Table4[[#This Row],[Team]]) -> 485000 | H3: =Table4[[#This Row],[Fabric Cons]]*Table4[[#This Row],[Fab Price]] -> 0 | K3: =Table4[[#This Row],[Pocket Cons]]*Table4[[#This Row],[Pocketing Price]] -> 0 | Q3: =P3*E3 -> 0 | V3: =(H3+K3+L3+O3)*U3% -> 0 | Y3: =IFERROR(X3/AB3,0) -> 0 | Z3: =Table4[[#This Row],[Target FOB]]-Table4[[#This Row],[Cost Price]] -> 0 | AA3: =IFERROR(Table4[[#This Row],[Total SAM]]/$Q$36,0) -> 0 | AB3: =SUM(V3:X3,R3:T3,K3:O3,H3) -> 0 | AC3: =AF3-AB3 -> 0 | AE3: 0 | AF3: =Table4[[#This Row],[Provided FOB]]+Table4[[#This Row],[Addition]] -> 0 | AG3: =Z3+S3 -> 0 | AH3: =IFERROR(AJ3*AN3/Q3,0) -> 0 | AI3: =IFERROR(Table4[[#This Row],[Per Min CM ]]/Table4[[#This Row],[Parity Rate]],0)*100 -> 0 | AJ3: =AG3*E3 -> 0 | AK3: =AJ3*AN3 -> 0 | AL3: =IFERROR(AK3/Q3,0) -> 0 | AM3: =AF3*E3 -> 0 | AO3: =Z3*E3 -> 0 | AP3: =$E3*H3*(1+$U3%) -> 0 | AQ3: =$E3*K3*(1+$U3%) -> 0 | AR3: =$E3*L3*(1+$U3%) -> 0 | AS3: =$E3*M3 -> 0 | AT3: =$E3*N3 -> 0 | AU3: =$E3*O3*(1+$U3%) -> 0 | AV3: =$E3*R3 -> 0 | AW3: =$E3*T3 -> 0 | AX3: =$E3*W3 -> 0 | AY3: =$E3*X3 -> 0 | AZ3: =SUM(AP3:AY3) -> 0 | BA3: =AM3-AZ3 -> 0 | BB3: =Table4[[#This Row],[OH ]]*Table4[[#This Row],[Qty]] -> 0 | BC3: =Table4[[#This Row],[Total Contribution]]-Table4[[#This Row],[Overheads]] -> 0 | BD3: =B3&D3 -> DENIMNAME IT | BE3: =AJ3-BA3 -> 0
A4: ='Month Wise Sales Qty'!A4 -> NAQEEB | B4: ='Month Wise Sales Qty'!B4 -> NON DENIM | D4: ='Month Wise Sales Qty'!C4 -> Vero Moda | E4: =SUMIFS('Month Wise Sales Qty'!P:P,'Month Wise Sales Qty'!C:C,Table4[[#This Row],[Customer]],'Month Wise Sales Qty'!B:B,Table4[[#This Row],[Wash Type]],'Month Wise Sales Qty'!A:A,Table4[[#This Row],[Team]]) -> 35000 | H4: =Table4[[#This Row],[Fabric Cons]]*Table4[[#This Row],[Fab Price]] -> 0 | K4: =Table4[[#This Row],[Pocket Cons]]*Table4[[#This Row],[Pocketing Price]] -> 0 | Q4: =P4*E4 -> 0 | V4: =(H4+K4+L4+O4)*U4% -> 0 | Y4: =IFERROR(X4/AB4,0) -> 0 | Z4: =Table4[[#This Row],[Target FOB]]-Table4[[#This Row],[Cost Price]] -> 0 | AA4: =IFERROR(Table4[[#This Row],[Total SAM]]/$Q$36,0) -> 0 | AB4: =SUM(V4:X4,R4:T4,K4:O4,H4) -> 0 | AC4: =AF4-AB4 -> 0 | AE4: 0 | AF4: =Table4[[#This Row],[Provided FOB]]+Table4[[#This Row],[Addition]] -> 0 | AG4: =Z4+S4 -> 0 | AH4: =IFERROR(AJ4*AN4/Q4,0) -> 0 | AI4: =IFERROR(Table4[[#This Row],[Per Min CM ]]/Table4[[#This Row],[Parity Rate]],0)*100 -> 0 | AJ4: =AG4*E4 -> 0 | AK4: =AJ4*AN4 -> 0 | AL4: =IFERROR(AK4/Q4,0) -> 0 | AM4: =AF4*E4 -> 0 | AO4: =Z4*E4 -> 0 | AP4: =$E4*H4*(1+$U4%) -> 0 | AQ4: =$E4*K4*(1+$U4%) -> 0 | AR4: =$E4*L4*(1+$U4%) -> 0 | AS4: =$E4*M4 -> 0 | AT4: =$E4*N4 -> 0 | AU4: =$E4*O4*(1+$U4%) -> 0 | AV4: =$E4*R4 -> 0 | AW4: =$E4*T4 -> 0 | AX4: =$E4*W4 -> 0 | AY4: =$E4*X4 -> 0 | AZ4: =SUM(AP4:AY4) -> 0 | BA4: =AM4-AZ4 -> 0 | BB4: =Table4[[#This Row],[OH ]]*Table4[[#This Row],[Qty]] -> 0 | BC4: =Table4[[#This Row],[Total Contribution]]-Table4[[#This Row],[Overheads]] -> 0 | BD4: =B4&D4 -> NON DENIMVero Moda | BE4: =AJ4-BA4 -> 0
A5: ='Month Wise Sales Qty'!A5 -> NAQEEB | B5: ='Month Wise Sales Qty'!B5 -> DENIM | D5: ='Month Wise Sales Qty'!C5 -> BLACK DIAMOND | E5: =SUMIFS('Month Wise Sales Qty'!P:P,'Month Wise Sales Qty'!C:C,Table4[[#This Row],[Customer]],'Month Wise Sales Qty'!B:B,Table4[[#This Row],[Wash Type]],'Month Wise Sales Qty'!A:A,Table4[[#This Row],[Team]]) -> 126000 | H5: =Table4[[#This Row],[Fabric Cons]]*Table4[[#This Row],[Fab Price]] -> 0 | K5: =Table4[[#This Row],[Pocket Cons]]*Table4[[#This Row],[Pocketing Price]] -> 0 | Q5: =P5*E5 -> 0 | V5: =(H5+K5+L5+O5)*U5% -> 0 | Y5: =IFERROR(X5/AB5,0) -> 0 | Z5: =Table4[[#This Row],[Target FOB]]-Table4[[#This Row],[Cost Price]] -> 0 | AA5: =IFERROR(Table4[[#This Row],[Total SAM]]/$Q$36,0) -> 0 | AB5: =SUM(V5:X5,R5:T5,K5:O5,H5) -> 0 | AC5: =AF5-AB5 -> 0 | AE5: 0 | AF5: =Table4[[#This Row],[Provided FOB]]+Table4[[#This Row],[Addition]] -> 0 | AG5: =Z5+S5 -> 0 | AH5: =IFERROR(AJ5*AN5/Q5,0) -> 0 | AI5: =IFERROR(Table4[[#This Row],[Per Min CM ]]/Table4[[#This Row],[Parity Rate]],0)*100 -> 0 | AJ5: =AG5*E5 -> 0 | AK5: =AJ5*AN5 -> 0 | AL5: =IFERROR(AK5/Q5,0) -> 0 | AM5: =AF5*E5 -> 0 | AO5: =Z5*E5 -> 0 | AP5: =$E5*H5*(1+$U5%) -> 0 | AQ5: =$E5*K5*(1+$U5%) -> 0 | AR5: =$E5*L5*(1+$U5%) -> 0 | AS5: =$E5*M5 -> 0 | AT5: =$E5*N5 -> 0 | AU5: =$E5*O5*(1+$U5%) -> 0 | AV5: =$E5*R5 -> 0 | AW5: =$E5*T5 -> 0 | AX5: =$E5*W5 -> 0 | AY5: =$E5*X5 -> 0 | AZ5: =SUM(AP5:AY5) -> 0 | BA5: =AM5-AZ5 -> 0 | BB5: =Table4[[#This Row],[OH ]]*Table4[[#This Row],[Qty]] -> 0 | BC5: =Table4[[#This Row],[Total Contribution]]-Table4[[#This Row],[Overheads]] -> 0 | BD5: =B5&D5 -> DENIMBLACK DIAMOND | BE5: =AJ5-BA5 -> 0
A6: ='Month Wise Sales Qty'!A6 -> NAQEEB | B6: ='Month Wise Sales Qty'!B6 -> NON DENIM | D6: ='Month Wise Sales Qty'!C6 -> GLORIA JEANS | E6: =SUMIFS('Month Wise Sales Qty'!P:P,'Month Wise Sales Qty'!C:C,Table4[[#This Row],[Customer]],'Month Wise Sales Qty'!B:B,Table4[[#This Row],[Wash Type]],'Month Wise Sales Qty'!A:A,Table4[[#This Row],[Team]]) -> 42500 | H6: =Table4[[#This Row],[Fabric Cons]]*Table4[[#This Row],[Fab Price]] -> 0 | K6: =Table4[[#This Row],[Pocket Cons]]*Table4[[#This Row],[Pocketing Price]] -> 0 | Q6: =P6*E6 -> 0 | V6: =(H6+K6+L6+O6)*U6% -> 0 | Y6: =IFERROR(X6/AB6,0) -> 0 | Z6: =Table4[[#This Row],[Target FOB]]-Table4[[#This Row],[Cost Price]] -> 0 | AA6: =IFERROR(Table4[[#This Row],[Total SAM]]/$Q$36,0) -> 0 | AB6: =SUM(V6:X6,R6:T6,K6:O6,H6) -> 0 | AC6: =AF6-AB6 -> 0 | AE6: 0 | AF6: =Table4[[#This Row],[Provided FOB]]+Table4[[#This Row],[Addition]] -> 0 | AG6: =Z6+S6 -> 0 | AH6: =IFERROR(AJ6*AN6/Q6,0) -> 0 | AI6: =IFERROR(Table4[[#This Row],[Per Min CM ]]/Table4[[#This Row],[Parity Rate]],0)*100 -> 0 | AJ6: =AG6*E6 -> 0 | AK6: =AJ6*AN6 -> 0 | AL6: =IFERROR(AK6/Q6,0) -> 0 | AM6: =AF6*E6 -> 0 | AO6: =Z6*E6 -> 0 | AP6: =$E6*H6*(1+$U6%) -> 0 | AQ6: =$E6*K6*(1+$U6%) -> 0 | AR6: =$E6*L6*(1+$U6%) -> 0 | AS6: =$E6*M6 -> 0 | AT6: =$E6*N6 -> 0 | AU6: =$E6*O6*(1+$U6%) -> 0 | AV6: =$E6*R6 -> 0 | AW6: =$E6*T6 -> 0 | AX6: =$E6*W6 -> 0 | AY6: =$E6*X6 -> 0 | AZ6: =SUM(AP6:AY6) -> 0 | BA6: =AM6-AZ6 -> 0 | BB6: =Table4[[#This Row],[OH ]]*Table4[[#This Row],[Qty]] -> 0 | BC6: =Table4[[#This Row],[Total Contribution]]-Table4[[#This Row],[Overheads]] -> 0 | BD6: =B6&D6 -> NON DENIMGLORIA JEANS | BE6: =AJ6-BA6 -> 0
A7: ='Month Wise Sales Qty'!A7 -> NAQEEB | B7: ='Month Wise Sales Qty'!B7 -> NON DENIM | D7: ='Month Wise Sales Qty'!C7 -> NEMESIS | E7: =SUMIFS('Month Wise Sales Qty'!P:P,'Month Wise Sales Qty'!C:C,Table4[[#This Row],[Customer]],'Month Wise Sales Qty'!B:B,Table4[[#This Row],[Wash Type]],'Month Wise Sales Qty'!A:A,Table4[[#This Row],[Team]]) -> 59000 | H7: =Table4[[#This Row],[Fabric Cons]]*Table4[[#This Row],[Fab Price]] -> 0 | K7: =Table4[[#This Row],[Pocket Cons]]*Table4[[#This Row],[Pocketing Price]] -> 0 | Q7: =P7*E7 -> 0 | V7: =(H7+K7+L7+O7)*U7% -> 0 | Y7: =IFERROR(X7/AB7,0) -> 0 | Z7: =Table4[[#This Row],[Target FOB]]-Table4[[#This Row],[Cost Price]] -> 0 | AA7: =IFERROR(Table4[[#This Row],[Total SAM]]/$Q$36,0) -> 0 | AB7: =SUM(V7:X7,R7:T7,K7:O7,H7) -> 0 | AC7: =AF7-AB7 -> 0 | AE7: 0 | AF7: =Table4[[#This Row],[Provided FOB]]+Table4[[#This Row],[Addition]] -> 0 | AG7: =Z7+S7 -> 0 | AH7: =IFERROR(AJ7*AN7/Q7,0) -> 0 | AI7: =IFERROR(Table4[[#This Row],[Per Min CM ]]/Table4[[#This Row],[Parity Rate]],0)*100 -> 0 | AJ7: =AG7*E7 -> 0 | AK7: =AJ7*AN7 -> 0 | AL7: =IFERROR(AK7/Q7,0) -> 0 | AM7: =AF7*E7 -> 0 | AO7: =Z7*E7 -> 0 | AP7: =$E7*H7*(1+$U7%) -> 0 | AQ7: =$E7*K7*(1+$U7%) -> 0 | AR7: =$E7*L7*(1+$U7%) -> 0 | AS7: =$E7*M7 -> 0 | AT7: =$E7*N7 -> 0 | AU7: =$E7*O7*(1+$U7%) -> 0 | AV7: =$E7*R7 -> 0 | AW7: =$E7*T7 -> 0 | AX7: =$E7*W7 -> 0 | AY7: =$E7*X7 -> 0 | AZ7: =SUM(AP7:AY7) -> 0 | BA7: =AM7-AZ7 -> 0 | BB7: =Table4[[#This Row],[OH ]]*Table4[[#This Row],[Qty]] -> 0 | BC7: =Table4[[#This Row],[Total Contribution]]-Table4[[#This Row],[Overheads]] -> 0 | BD7: =B7&D7 -> NON DENIMNEMESIS | BE7: =AJ7-BA7 -> 0
A8: ='Month Wise Sales Qty'!A8 -> RIZWAN | B8: ='Month Wise Sales Qty'!B8 -> DENIM | D8: ='Month Wise Sales Qty'!C8 -> HERO/STOOKER | E8: =SUMIFS('Month Wise Sales Qty'!P:P,'Month Wise Sales Qty'!C:C,Table4[[#This Row],[Customer]],'Month Wise Sales Qty'!B:B,Table4[[#This Row],[Wash Type]],'Month Wise Sales Qty'!A:A,Table4[[#This Row],[Team]]) -> 629000 | H8: =Table4[[#This Row],[Fabric Cons]]*Table4[[#This Row],[Fab Price]] -> 0 | K8: =Table4[[#This Row],[Pocket Cons]]*Table4[[#This Row],[Pocketing Price]] -> 0 | Q8: =P8*E8 -> 0 | V8: =(H8+K8+L8+O8)*U8% -> 0 | Y8: =IFERROR(X8/AB8,0) -> 0 | Z8: =Table4[[#This Row],[Target FOB]]-Table4[[#This Row],[Cost Price]] -> 0 | AA8: =IFERROR(Table4[[#This Row],[Total SAM]]/$Q$36,0) -> 0 | AB8: =SUM(V8:X8,R8:T8,K8:O8,H8) -> 0 | AC8: =AF8-AB8 -> 0 | AE8: 0 | AF8: =Table4[[#This Row],[Provided FOB]]+Table4[[#This Row],[Addition]] -> 0 | AG8: =Z8+S8 -> 0 | AH8: =IFERROR(AJ8*AN8/Q8,0) -> 0 | AI8: =IFERROR(Table4[[#This Row],[Per Min CM ]]/Table4[[#This Row],[Parity Rate]],0)*100 -> 0 | AJ8: =AG8*E8 -> 0 | AK8: =AJ8*AN8 -> 0 | AL8: =IFERROR(AK8/Q8,0) -> 0 | AM8: =AF8*E8 -> 0 | AO8: =Z8*E8 -> 0 | AP8: =$E8*H8*(1+$U8%) -> 0 | AQ8: =$E8*K8*(1+$U8%) -> 0 | AR8: =$E8*L8*(1+$U8%) -> 0 | AS8: =$E8*M8 -> 0 | AT8: =$E8*N8 -> 0 | AU8: =$E8*O8*(1+$U8%) -> 0 | AV8: =$E8*R8 -> 0 | AW8: =$E8*T8 -> 0 | AX8: =$E8*W8 -> 0 | AY8: =$E8*X8 -> 0 | AZ8: =SUM(AP8:AY8) -> 0 | BA8: =AM8-AZ8 -> 0 | BB8: =Table4[[#This Row],[OH ]]*Table4[[#This Row],[Qty]] -> 0 | BC8: =Table4[[#This Row],[Total Contribution]]-Table4[[#This Row],[Overheads]] -> 0 | BD8: =B8&D8 -> DENIMHERO/STOOKER | BE8: =AJ8-BA8 -> 0
A9: ='Month Wise Sales Qty'!A9 -> RIZWAN | B9: ='Month Wise Sales Qty'!B9 -> NON DENIM | D9: ='Month Wise Sales Qty'!C9 -> SORBINO | E9: =SUMIFS('Month Wise Sales Qty'!P:P,'Month Wise Sales Qty'!C:C,Table4[[#This Row],[Customer]],'Month Wise Sales Qty'!B:B,Table4[[#This Row],[Wash Type]],'Month Wise Sales Qty'!A:A,Table4[[#This Row],[Team]]) -> 285000 | H9: =Table4[[#This Row],[Fabric Cons]]*Table4[[#This Row],[Fab Price]] -> 0 | K9: =Table4[[#This Row],[Pocket Cons]]*Table4[[#This Row],[Pocketing Price]] -> 0 | Q9: =P9*E9 -> 0 | V9: =(H9+K9+L9+O9)*U9% -> 0 | Y9: =IFERROR(X9/AB9,0) -> 0 | Z9: =Table4[[#This Row],[Target FOB]]-Table4[[#This Row],[Cost Price]] -> 0 | AA9: =IFERROR(Table4[[#This Row],[Total SAM]]/$Q$36,0) -> 0 | AB9: =SUM(V9:X9,R9:T9,K9:O9,H9) -> 0 | AC9: =AF9-AB9 -> 0 | AE9: 0 | AF9: =Table4[[#This Row],[Provided FOB]]+Table4[[#This Row],[Addition]] -> 0 | AG9: =Z9+S9 -> 0 | AH9: =IFERROR(AJ9*AN9/Q9,0) -> 0 | AI9: =IFERROR(Table4[[#This Row],[Per Min CM ]]/Table4[[#This Row],[Parity Rate]],0)*100 -> 0 | AJ9: =AG9*E9 -> 0 | AK9: =AJ9*AN9 -> 0 | AL9: =IFERROR(AK9/Q9,0) -> 0 | AM9: =AF9*E9 -> 0 | AO9: =Z9*E9 -> 0 | AP9: =$E9*H9*(1+$U9%) -> 0 | AQ9: =$E9*K9*(1+$U9%) -> 0 | AR9: =$E9*L9*(1+$U9%) -> 0 | AS9: =$E9*M9 -> 0 | AT9: =$E9*N9 -> 0 | AU9: =$E9*O9*(1+$U9%) -> 0 | AV9: =$E9*R9 -> 0 | AW9: =$E9*T9 -> 0 | AX9: =$E9*W9 -> 0 | AY9: =$E9*X9 -> 0 | AZ9: =SUM(AP9:AY9) -> 0 | BA9: =AM9-AZ9 -> 0 | BB9: =Table4[[#This Row],[OH ]]*Table4[[#This Row],[Qty]] -> 0 | BC9: =Table4[[#This Row],[Total Contribution]]-Table4[[#This Row],[Overheads]] -> 0 | BD9: =B9&D9 -> NON DENIMSORBINO | BE9: =AJ9-BA9 -> 0
A10: ='Month Wise Sales Qty'!A10 -> RIZWAN | B10: ='Month Wise Sales Qty'!B10 -> NON DENIM | D10: ='Month Wise Sales Qty'!C10 -> ELVIN | E10: =SUMIFS('Month Wise Sales Qty'!P:P,'Month Wise Sales Qty'!C:C,Table4[[#This Row],[Customer]],'Month Wise Sales Qty'!B:B,Table4[[#This Row],[Wash Type]],'Month Wise Sales Qty'!A:A,Table4[[#This Row],[Team]]) -> 115000 | H10: =Table4[[#This Row],[Fabric Cons]]*Table4[[#This Row],[Fab Price]] -> 0 | K10: =Table4[[#This Row],[Pocket Cons]]*Table4[[#This Row],[Pocketing Price]] -> 0 | Q10: =P10*E10 -> 0 | V10: =(H10+K10+L10+O10)*U10% -> 0 | Y10: =IFERROR(X10/AB10,0) -> 0 | Z10: =Table4[[#This Row],[Target FOB]]-Table4[[#This Row],[Cost Price]] -> 0 | AA10: =IFERROR(Table4[[#This Row],[Total SAM]]/$Q$36,0) -> 0 | AB10: =SUM(V10:X10,R10:T10,K10:O10,H10) -> 0 | AC10: =AF10-AB10 -> 0 | AE10: 0 | AF10: =Table4[[#This Row],[Provided FOB]]+Table4[[#This Row],[Addition]] -> 0 | AG10: =Z10+S10 -> 0 | AH10: =IFERROR(AJ10*AN10/Q10,0) -> 0 | AI10: =IFERROR(Table4[[#This Row],[Per Min CM ]]/Table4[[#This Row],[Parity Rate]],0)*100 -> 0 | AJ10: =AG10*E10 -> 0 | AK10: =AJ10*AN10 -> 0 | AL10: =IFERROR(AK10/Q10,0) -> 0 | AM10: =AF10*E10 -> 0 | AO10: =Z10*E10 -> 0 | AP10: =$E10*H10*(1+$U10%) -> 0 | AQ10: =$E10*K10*(1+$U10%) -> 0 | AR10: =$E10*L10*(1+$U10%) -> 0 | AS10: =$E10*M10 -> 0 | AT10: =$E10*N10 -> 0 | AU10: =$E10*O10*(1+$U10%) -> 0 | AV10: =$E10*R10 -> 0 | AW10: =$E10*T10 -> 0 | AX10: =$E10*W10 -> 0 | AY10: =$E10*X10 -> 0 | AZ10: =SUM(AP10:AY10) -> 0 | BA10: =AM10-AZ10 -> 0 | BB10: =Table4[[#This Row],[OH ]]*Table4[[#This Row],[Qty]] -> 0 | BC10: =Table4[[#This Row],[Total Contribution]]-Table4[[#This Row],[Overheads]] -> 0 | BD10: =B10&D10 -> NON DENIMELVIN | BE10: =AJ10-BA10 -> 0
A11: ='Month Wise Sales Qty'!A11 -> RIZWAN | B11: ='Month Wise Sales Qty'!B11 -> DENIM | D11: ='Month Wise Sales Qty'!C11 -> ORIGINAL MARINE | E11: =SUMIFS('Month Wise Sales Qty'!P:P,'Month Wise Sales Qty'!C:C,Table4[[#This Row],[Customer]],'Month Wise Sales Qty'!B:B,Table4[[#This Row],[Wash Type]],'Month Wise Sales Qty'!A:A,Table4[[#This Row],[Team]]) -> 75000 | H11: =Table4[[#This Row],[Fabric Cons]]*Table4[[#This Row],[Fab Price]] -> 0 | K11: =Table4[[#This Row],[Pocket Cons]]*Table4[[#This Row],[Pocketing Price]] -> 0 | Q11: =P11*E11 -> 0 | V11: =(H11+K11+L11+O11)*U11% -> 0 | Y11: =IFERROR(X11/AB11,0) -> 0 | Z11: =Table4[[#This Row],[Target FOB]]-Table4[[#This Row],[Cost Price]] -> 0 | AA11: =IFERROR(Table4[[#This Row],[Total SAM]]/$Q$36,0) -> 0 | AB11: =SUM(V11:X11,R11:T11,K11:O11,H11) -> 0 | AC11: =AF11-AB11 -> 0 | AE11: 0 | AF11: =Table4[[#This Row],[Provided FOB]]+Table4[[#This Row],[Addition]] -> 0 | AG11: =Z11+S11 -> 0 | AH11: =IFERROR(AJ11*AN11/Q11,0) -> 0 | AI11: =IFERROR(Table4[[#This Row],[Per Min CM ]]/Table4[[#This Row],[Parity Rate]],0)*100 -> 0 | AJ11: =AG11*E11 -> 0 | AK11: =AJ11*AN11 -> 0 | AL11: =IFERROR(AK11/Q11,0) -> 0 | AM11: =AF11*E11 -> 0 | AO11: =Z11*E11 -> 0 | AP11: =$E11*H11*(1+$U11%) -> 0 | AQ11: =$E11*K11*(1+$U11%) -> 0 | AR11: =$E11*L11*(1+$U11%) -> 0 | AS11: =$E11*M11 -> 0 | AT11: =$E11*N11 -> 0 | AU11: =$E11*O11*(1+$U11%) -> 0 | AV11: =$E11*R11 -> 0 | AW11: =$E11*T11 -> 0 | AX11: =$E11*W11 -> 0 | AY11: =$E11*X11 -> 0 | AZ11: =SUM(AP11:AY11) -> 0 | BA11: =AM11-AZ11 -> 0 | BB11: =Table4[[#This Row],[OH ]]*Table4[[#This Row],[Qty]] -> 0 | BC11: =Table4[[#This Row],[Total Contribution]]-Table4[[#This Row],[Overheads]] -> 0 | BD11: =B11&D11 -> DENIMORIGINAL MARINE | BE11: =AJ11-BA11 -> 0
A12: ='Month Wise Sales Qty'!A12 -> RIZWAN | B12: ='Month Wise Sales Qty'!B12 -> NON DENIM | D12: ='Month Wise Sales Qty'!C12 -> SWING JEANS | E12: =SUMIFS('Month Wise Sales Qty'!P:P,'Month Wise Sales Qty'!C:C,Table4[[#This Row],[Customer]],'Month Wise Sales Qty'!B:B,Table4[[#This Row],[Wash Type]],'Month Wise Sales Qty'!A:A,Table4[[#This Row],[Team]]) -> 80000 | H12: =Table4[[#This Row],[Fabric Cons]]*Table4[[#This Row],[Fab Price]] -> 0 | K12: =Table4[[#This Row],[Pocket Cons]]*Table4[[#This Row],[Pocketing Price]] -> 0 | Q12: =P12*E12 -> 0 | V12: =(H12+K12+L12+O12)*U12% -> 0 | Y12: =IFERROR(X12/AB12,0) -> 0 | Z12: =Table4[[#This Row],[Target FOB]]-Table4[[#This Row],[Cost Price]] -> 0 | AA12: =IFERROR(Table4[[#This Row],[Total SAM]]/$Q$36,0) -> 0 | AB12: =SUM(V12:X12,R12:T12,K12:O12,H12) -> 0 | AC12: =AF12-AB12 -> 0 | AE12: 0 | AF12: =Table4[[#This Row],[Provided FOB]]+Table4[[#This Row],[Addition]] -> 0 | AG12: =Z12+S12 -> 0 | AH12: =IFERROR(AJ12*AN12/Q12,0) -> 0 | AI12: =IFERROR(Table4[[#This Row],[Per Min CM ]]/Table4[[#This Row],[Parity Rate]],0)*100 -> 0 | AJ12: =AG12*E12 -> 0 | AK12: =AJ12*AN12 -> 0 | AL12: =IFERROR(AK12/Q12,0) -> 0 | AM12: =AF12*E12 -> 0 | AO12: =Z12*E12 -> 0 | AP12: =$E12*H12*(1+$U12%) -> 0 | AQ12: =$E12*K12*(1+$U12%) -> 0 | AR12: =$E12*L12*(1+$U12%) -> 0 | AS12: =$E12*M12 -> 0 | AT12: =$E12*N12 -> 0 | AU12: =$E12*O12*(1+$U12%) -> 0 | AV12: =$E12*R12 -> 0 | AW12: =$E12*T12 -> 0 | AX12: =$E12*W12 -> 0 | AY12: =$E12*X12 -> 0 | AZ12: =SUM(AP12:AY12) -> 0 | BA12: =AM12-AZ12 -> 0 | BB12: =Table4[[#This Row],[OH ]]*Table4[[#This Row],[Qty]] -> 0 | BC12: =Table4[[#This Row],[Total Contribution]]-Table4[[#This Row],[Overheads]] -> 0 | BD12: =B12&D12 -> NON DENIMSWING JEANS | BE12: =AJ12-BA12 -> 0
A13: ='Month Wise Sales Qty'!A13 -> RIZWAN | B13: ='Month Wise Sales Qty'!B13 -> DENIM | D13: ='Month Wise Sales Qty'!C13 -> NEW YORKER | E13: =SUMIFS('Month Wise Sales Qty'!P:P,'Month Wise Sales Qty'!C:C,Table4[[#This Row],[Customer]],'Month Wise Sales Qty'!B:B,Table4[[#This Row],[Wash Type]],'Month Wise Sales Qty'!A:A,Table4[[#This Row],[Team]]) -> 506000 | H13: =Table4[[#This Row],[Fabric Cons]]*Table4[[#This Row],[Fab Price]] -> 0 | K13: =Table4[[#This Row],[Pocket Cons]]*Table4[[#This Row],[Pocketing Price]] -> 0 | Q13: =P13*E13 -> 0 | V13: =(H13+K13+L13+O13)*U13% -> 0 | Y13: =IFERROR(X13/AB13,0) -> 0 | Z13: =Table4[[#This Row],[Target FOB]]-Table4[[#This Row],[Cost Price]] -> 0 | AA13: =IFERROR(Table4[[#This Row],[Total SAM]]/$Q$36,0) -> 0 | AB13: =SUM(V13:X13,R13:T13,K13:O13,H13) -> 0 | AC13: =AF13-AB13 -> 0 | AE13: 0 | AF13: =Table4[[#This Row],[Provided FOB]]+Table4[[#This Row],[Addition]] -> 0 | AG13: =Z13+S13 -> 0 | AH13: =IFERROR(AJ13*AN13/Q13,0) -> 0 | AI13: =IFERROR(Table4[[#This Row],[Per Min CM ]]/Table4[[#This Row],[Parity Rate]],0)*100 -> 0 | AJ13: =AG13*E13 -> 0 | AK13: =AJ13*AN13 -> 0 | AL13: =IFERROR(AK13/Q13,0) -> 0 | AM13: =AF13*E13 -> 0 | AO13: =Z13*E13 -> 0 | AP13: =$E13*H13*(1+$U13%) -> 0 | AQ13: =$E13*K13*(1+$U13%) -> 0 | AR13: =$E13*L13*(1+$U13%) -> 0 | AS13: =$E13*M13 -> 0 | AT13: =$E13*N13 -> 0 | AU13: =$E13*O13*(1+$U13%) -> 0 | AV13: =$E13*R13 -> 0 | AW13: =$E13*T13 -> 0 | AX13: =$E13*W13 -> 0 | AY13: =$E13*X13 -> 0 | AZ13: =SUM(AP13:AY13) -> 0 | BA13: =AM13-AZ13 -> 0 | BB13: =Table4[[#This Row],[OH ]]*Table4[[#This Row],[Qty]] -> 0 | BC13: =Table4[[#This Row],[Total Contribution]]-Table4[[#This Row],[Overheads]] -> 0 | BD13: =B13&D13 -> DENIMNEW YORKER | BE13: =AJ13-BA13 -> 0
... A34: ='Month Wise Sales Qty'!A34 -> FARRUKH | B34: ='Month Wise Sales Qty'!B34 -> NON DENIM | D34: ='Month Wise Sales Qty'!C34 -> C&A-KIDS | E34: =SUMIFS('Month Wise Sales Qty'!P:P,'Month Wise Sales Qty'!C:C,Table4[[#This Row],[Customer]],'Month Wise Sales Qty'!B:B,Table4[[#This Row],[Wash Type]],'Month Wise Sales Qty'!A:A,Table4[[#This Row],[Team]]) -> 80000 | H34: =Table4[[#This Row],[Fabric Cons]]*Table4[[#This Row],[Fab Price]] -> 0 | K34: =Table4[[#This Row],[Pocket Cons]]*Table4[[#This Row],[Pocketing Price]] -> 0 | Q34: =P34*E34 -> 0 | V34: =(H34+K34+L34+O34)*U34% -> 0 | Y34: =IFERROR(X34/AB34,0) -> 0 | Z34: =Table4[[#This Row],[Target FOB]]-Table4[[#This Row],[Cost Price]] -> 0 | AA34: =IFERROR(Table4[[#This Row],[Total SAM]]/$Q$36,0) -> 0 | AB34: =SUM(V34:X34,R34:T34,K34:O34,H34) -> 0 | AC34: =AF34-AB34 -> 0 | AE34: 0 | AF34: =Table4[[#This Row],[Provided FOB]]+Table4[[#This Row],[Addition]] -> 0 | AG34: =Z34+S34 -> 0 | AH34: =IFERROR(AJ34*AN34/Q34,0) -> 0 | AI34: =IFERROR(Table4[[#This Row],[Per Min CM ]]/Table4[[#This Row],[Parity Rate]],0)*100 -> 0 | AJ34: =AG34*E34 -> 0 | AK34: =AJ34*AN34 -> 0 | AL34: =IFERROR(AK34/Q34,0) -> 0 | AM34: =AF34*E34 -> 0 | AO34: =Z34*E34 -> 0 | AP34: =$E34*H34*(1+$U34%) -> 0 | AQ34: =$E34*K34*(1+$U34%) -> 0 | AR34: =$E34*L34*(1+$U34%) -> 0 | AS34: =$E34*M34 -> 0 | AT34: =$E34*N34 -> 0 | AU34: =$E34*O34*(1+$U34%) -> 0 | AV34: =$E34*R34 -> 0 | AW34: =$E34*T34 -> 0 | AX34: =$E34*W34 -> 0 | AY34: =$E34*X34 -> 0 | AZ34: =SUM(AP34:AY34) -> 0 | BA34: =AM34-AZ34 -> 0 | BB34: =Table4[[#This Row],[OH ]]*Table4[[#This Row],[Qty]] -> 0 | BC34: =Table4[[#This Row],[Total Contribution]]-Table4[[#This Row],[Overheads]] -> 0 | BD34: =B34&D34 -> NON DENIMC&A-KIDS | BE34: =AJ34-BA34 -> 0
E36: =SUBTOTAL(109,Table4[Qty]) -> 8597384.3 | F36: =SUMPRODUCT(Table4[Qty],Table4[Fabric Cons])/E36 -> 0 | G36: =SUMPRODUCT(Table4[Fab Price],Table4[Qty])/E36 -> 0 | H36: =SUMPRODUCT(Table4[Fabric],Table4[Qty])/E36 -> 0 | I36: =SUMPRODUCT(Table4[Pocket Cons],Table4[Qty])/E36 -> 0 | J36: =SUMPRODUCT(Table4[Pocketing Price],Table4[Qty])/E36 -> 0 | K36: =SUMPRODUCT(Table4[Pocketing],Table4[Qty])/E36 -> 0 | L36: =SUMPRODUCT(Table4[Trim],Table4[Qty])/E36 -> 0 | M36: =SUMPRODUCT(Table4[Testing],Table4[Qty])/E36 -> 0 | N36: =SUMPRODUCT(Table4[Sampling],Table4[Qty])/E36 -> 0 | O36: =SUMPRODUCT(Table4[Chemical],Table4[Qty])/E36 -> 0 | P36: =SUMPRODUCT(Table4[SAM],Table4[Qty])/E36 -> 0 | Q36: =SUBTOTAL(109,Table4[Total SAM]) -> 0 | R36: =SUMPRODUCT(Table4[Wash OH],Table4[Qty])/E36 -> 0 | S36: =SUMPRODUCT(Table4[[OH ]],Table4[Qty])/E36 -> 0 | T36: =SUMPRODUCT(Table4[Freight],Table4[Qty])/E36 -> 0 | V36: =SUMPRODUCT(Table4[Wastage],Table4[Qty])/E36 -> 0 | W36: =SUMPRODUCT(Table4[Finance Cost],Table4[Qty])/E36 -> 0 | X36: =SUMPRODUCT(Table4[Commission],Table4[Qty])/E36 -> 0 | Z36: =SUMPRODUCT(Table4[Profit],Table4[Qty])/E36 -> 0 | AA36: =SUMPRODUCT(Table4[Provided FOB],Table4[Qty])/E36 -> 0 | AC36: =SUMPRODUCT(Table4[Target FOB],Table4[Qty])/E36 -> 0 | AF36: =SUMPRODUCT(Table4[Target FOB],Table4[Qty])/E36 -> 0 | AG36: =(SUMPRODUCT(Table4[CM],Table4[Qty])/Q36)*100 -> #DIV/0! | AH36: =IFERROR(AJ36*AN36/Q36,0) -> 0 | AI36: =AL36/278*100 -> #DIV/0! | AJ36: =SUM(AJ2:AJ34) -> 0 | AK36: =SUM(AK2:AK34) -> 0 | AL36: =AK36/Q36 -> #DIV/0! | AM36: =SUM(AM2:AM34) -> 0 | AN36: =AN34 -> 0 | AO36: =SUM(AO2:AO34) -> 0 | AP36: =SUM(AP2:AP34) -> 0 | AQ36: =SUM(AQ2:AQ34) -> 0 | AR36: =SUM(AR2:AR34) -> 0 | AS36: =SUM(AS2:AS34) -> 0 | AT36: =SUM(AT2:AT34) -> 0 | AU36: =SUM(AU2:AU34) -> 0 | AV36: =SUM(AV2:AV34) -> 0 | ... BC36: =SUM(BC2:BC34) -> 0
Z37: =Z36/AF36 -> #DIV/0! | AK37: =SUMPRODUCT(Table4[[OH ]],Table4[Qty])*285 -> 0
